snoscience/__init__.py
snoscience/_activation.py
snoscience/_layers.py
snoscience/_loss.py
snoscience/_neurons.py
snoscience/metrics.py
snoscience/networks.py
snoscience-2.0.2.dist-info/METADATA
snoscience-2.0.2.dist-info/WHEEL
snoscience-2.0.2.dist-info/RECORD
